{
  "name": "Etta McCormick",
  "age": 25,
  "address": {
    "street": "Vefliw Loop",
    "city": "Ijibmo",
    "state": "PA",
    "zip": "88237"
  },
  "contact": {
    "phone": "(878) 456-5106",
    "servicePhone": "800886258"
  },
  "birthday": "1967-08-18T10:33:53.928Z",
  "ip": "197.209.139.238",
  "foo": "bar",
  "profile": {
    "about": "Popsultid ikazi wiwinpa nisuhkof wuwsamol bikiw gavagales jih del zetog wodog beuc fotutri mu akehade febah pokjomdu furu. Lipa luz tacah copgepup saguj ca nisoj alutu ta ehnaw po usa. De zok powcomwi gina hegup beaj il jonobwu fuvmad sis za ulivu. Uccavav vor rihniwak pem fakage bop miusug dewhik negep ij lih cejene asiubli uset. Uz ribhat pudpo nawihte ku mis cojfossep otimaw kusbugo jebhef gat wizaf.",
    "bio": "Nefateg dih ogiviwa ma gahuponiz ro tebezaw gusiz milkag tuanu enneaka tekemo hahvo wavba jijokoj riw wemutu doblod. Faj rocjofu notzew finakuvu mid top akpupteb belun si ejwup naabke ge vahsev saputih fofat de ac nam. Sozus jofoh vusahje borivim cunluw tef kuj cejeno op varbebba ji sehbew de beta umtegjat ku kobgondel juctor."
  },
  "apiKey": "f07d9f173fbb8054c1937771c4d24ddca48491b0516be82142a70b49553d2b37",
  "currency": {
    "code": "LTL",
    "name": "Lithuania Litas"
  }
}