{
  "name": "Charlie Ramsey",
  "age": 43,
  "address": {
    "street": "Fikjuc Circle",
    "city": "Dicihgug",
    "state": "LA",
    "zip": "83116"
  },
  "contact": {
    "phone": "(745) 619-2688",
    "servicePhone": "800735797"
  },
  "birthday": "1998-06-10T01:08:32.138Z",
  "ip": "255.13.4.201",
  "foo": "bar",
  "profile": {
    "about": "Adzi fi vavger ucvam lilamti dudto revuz zop be ig lez pug umaf za ejaagufat rejiruci refuzoho. Ikaporuc wicewzej itnufcag secwuduw aku loled dib acoonpo ozjuv cawriok law su gijep. Repehesa ukeabiek kocufu rel tolali isa irufemaz ramwaf zikaz eneado lefupo gianajej roudji hipoz naz iho. Wanafe tizhigzo zet pewarmu sirwac cot ro ta ben bide wecro ti vubwogfoz fiebaru povveg.",
    "bio": "Jiwi hep azkodaw fo po focdevoc di duwso eku jak jepecas bawbem. Vepma ceovotoh tekmaawa fuv zis ciczec puvbihtub fovin fa neweb basnebu ji ehigeze. Gad vaaci muctu wiwaz epa comdajji jagrugri ezucu suzatlej soja je pac gorir liz. Ti jocote ked to go zo hu totej uj mugeh wabrejsud lanahmuw nejpatul de muwbo gomcat ihuza. Gapsoshig eszij iw asi nujeke nufdir fuzcac loju ge vu lazfiajo tirajwo ruhtil novjishaj birvec. Esici muz fija ito hufnakub fewehtu fokde cak nitew hasepsed bejniba gegij ro rupegki izi. Emece to vij pewra sugke rakda we to lurdatni ge aseug mar neldorpe dehupo nosistel zop welomun."
  },
  "apiKey": "ec084c73eca89105a06192a1602a234bf1fac2a241eece84b32d3a0f3b15b3a7",
  "currency": {
    "code": "SZL",
    "name": "Swaziland Lilangeni"
  }
}