{
  "name": "Christine Willis",
  "age": 63,
  "address": {
    "street": "Zageh Ridge",
    "city": "Zakucu",
    "state": "HI",
    "zip": "19936"
  },
  "contact": {
    "phone": "(551) 203-7128",
    "servicePhone": "800282933"
  },
  "birthday": "1975-09-15T06:59:08.561Z",
  "ip": "23.117.139.184",
  "foo": "bar",
  "profile": {
    "about": "Ijeowi voctenbop vasu fosiv zuljuk gi kuz tuvbo hu pifij re tev onlinra ra urposfi re sosetwet. Huide tazuho ju vanor efurozu pen mopse ha igeoneij uvpueve rosukece gitil uzi poworof dusdut. Ih ema vaz la gamrog cannupiw omapihdev nonpe duwizne ino hi noozu if pufrer. Aku zevoh elojadvi poho icoipaso pe espas vin weilku nif ukdekaf emagu geunga gejajvu ju vewsu. Hi kien vitis zet ha ow pa pud iwkanow acumojul negep sacigo anamoppi. Vimerrud nertafo ihneb cibad hig jujtid wa lajcekiwa keb ejebonjon anote zumure dumze job nesivu vame tos ni.",
    "bio": "Ogajebut tejefi iframlo ridusotok ico hinjigfuk homaw on rolas fozsil ti jopejenec lih ripjup nizkec nezo. Bunof egoma jokcaj dof uk wewza tum bo fohias zammiz anoto tupbiek kuzaku eloojpov uwo gozusafa tulpafi ege. Duvzuoh feuc pa kuz fomomi potu siali od aprel cocja romwic becwocma vus hik vik biate pokvuzul."
  },
  "apiKey": "cebae7ba7f6ba915d724e9b9aa851dda793b495649ad104c5f10b580f767a587",
  "currency": {
    "code": "RON",
    "name": "Romania New Leu"
  }
}