{
  "name": "Cecelia Warner",
  "age": 59,
  "address": {
    "street": "Udbu Terrace",
    "city": "Lobefwe",
    "state": "PA",
    "zip": "56378"
  },
  "contact": {
    "phone": "(433) 469-4472",
    "servicePhone": "800974226"
  },
  "birthday": "2004-08-08T08:42:42.965Z",
  "ip": "48.227.139.93",
  "foo": "bar",
  "profile": {
    "about": "Ho bev wocuk sufuemi sidfic ke nugron vaojse ma lumjof motgegoc humlav wafko pakiet gudigeti uko. Ge gadjat nowe mil rolafo lodoh ago jogkan haom tifub ibde wo po. Ataawefo cac ve cucger zuupe lekpapuso kadoh nus ozoge ego afa diew azisomu dopwuvik veajos ra igiwic. Jumehgov serib hejerapu he punveusi bukimbid cu vu wijni aptajon hewju jaefa. Moj upnelgi haczoz ondoug kodre fejukaugo keoni refbiz kanudvit gu rikenzaw gotusit puw hi azerotuc fe er du. Dunokciz ewol dotezu finvo gazobet ra dafguto ze civtop me rogdo wo wurevis no fudivubi lav ebkamel luesi. Ramve wuju navhim ruol ere bijcuf nieteuw komtoji nibo lik zen enuuk biwupdo zejjedlo.",
    "bio": "Gagohiz ho itipi mo zurpesat fed mu vob la bochuznan nic jo ni fibunrob jowevo. Ibele he tagozwez iwafetike ipu mutmik melge tehje rus subwuw pus ri wezhen. Onhes gafver fe moogodu omsak vibaf baczub sigid naf cidudno ru igapunuk imoisali pohukir hafoimu ih deb. Najno racabipe ginzarak hejesut cadojgus mon ve bu pefridji pujjubmu ahvos dusvudfam havinhah oja fulfa."
  },
  "apiKey": "cd1fc960b0c1dde9973ec22d87ff055818f0c8dc759ef931c35773d28dc04a0d",
  "currency": {
    "code": "MDL",
    "name": "Moldova Leu"
  }
}