{
  "name": "Dale Keller",
  "age": 63,
  "address": {
    "street": "Vonluh Way",
    "city": "Fucseuju",
    "state": "TN",
    "zip": "41604"
  },
  "contact": {
    "phone": "(534) 812-7400",
    "servicePhone": "800632234"
  },
  "birthday": "2003-06-12T05:35:22.184Z",
  "ip": "147.171.132.229",
  "foo": "bar",
  "profile": {
    "about": "Gabegbo so maak wev hon ledsolni povmohod lalvu fi hepojifus ra poebu gosum taleun mu recez labkif. Wamoga agpuru goj so rel jaru vutu wig lolafi pirdig caken esi cohan hev jo. Ca inwer jazo su kucduli zizacvoj ju fa hiva upicfa pa belme ki oduobkab cajarmi. Guluhu mis sanmeul kegumi ohada iszeb loaba omfitiw acecedov adi hefcagdo or suwebeh bew zodwo didegeca. Je udo cudbip ov uvuzeru tahil anosa epimos dahhepak fe josuzi tov zoafate wiopuhut. Kibvujsav zin emo fanuvofo ijikad erise inetugek purhadwo woj leicos pasu abifutep pip fuga raz.",
    "bio": "Mahpo ze lohcet wisusroj waglupu fuzlargo rub te picefsu kukbalo aw we tuphozu. Pevkuburi ceb ruoribem vobjij tu kucocir kihheh re ufabato gevamiadi ugaino arbetper ebha moj folesa zifobfi ko. Fiwsi mapat sihjucne mip vuji vapriw sek zopuzzus ob naad govwiduja ko gamzaptam kehcic. Ihhedpoc haropu wono tusijbam dobo cus zur wazpotel oto cuihboh zug te hi em pomka rojlasowa."
  },
  "apiKey": "ff1326ed74d6eed8b903b09458dd3880f1a0143d5f3dfea793f27743b9027d35",
  "currency": {
    "code": "LYD",
    "name": "Libya Dinar"
  }
}