{
  "name": "Franklin Robbins",
  "age": 56,
  "address": {
    "street": "Lowdo Pass",
    "city": "Ibvida",
    "state": "AK",
    "zip": "92124"
  },
  "contact": {
    "phone": "(651) 580-2833",
    "servicePhone": "800725413"
  },
  "birthday": "1998-12-05T03:27:04.638Z",
  "ip": "133.245.228.140",
  "foo": "bar",
  "profile": {
    "about": "Anija wiwkebo woek tijobo jiszo kohri secvifvol jo javece utga vaku tocfatu pekicmok joj. Nonasu dondiwe na mafumu akaja za rovonik wo sokfi aktic ojho loghuuco wo mu vasec bifgazu harbovma dacmam. Enepoki zazeddos eki hubwecib ak to neztejguk tabfod jibov ci lowli pitjifha bego gegep rufgu reczuzi sino sasraw. Sipci sunbew uworot ezfe juf ub muvowjo sed ic abgiw rotisi lu hulhim wabwuave.",
    "bio": "No wiukute ow ifobakwab doso jaepazu ipopu bemilu soiklo ka weg ozdugwoh nupi loz viri zuc bupi ma. Ic nuwumaj vic radabohel zaki beutuoj kafi nar ebjofco ni mikpil evitil. Va kapugfo cirzi nifavpi na wospabe lihjal umsiom silojen hocdoji igikaju seakepaw veir. Sukmiv famzun wiruju pefej fi ocisaesu pe duduj fu odiak jiwpu eniwuini zit ubfi ruk cu po."
  },
  "apiKey": "1e5cf972d27a160a2195f0aed8f0be6c542824930c8e268880ffbb95762ca253",
  "currency": {
    "code": "TVD",
    "name": "Tuvalu Dollar"
  }
}