{
  "name": "Eunice Bradley",
  "age": 59,
  "address": {
    "street": "Agepon Path",
    "city": "Velvisu",
    "state": "MT",
    "zip": "85210"
  },
  "contact": {
    "phone": "(618) 513-7049",
    "servicePhone": "800477565"
  },
  "birthday": "1994-08-27T12:22:47.899Z",
  "ip": "149.222.73.219",
  "foo": "bar",
  "profile": {
    "about": "Gopvabsow seihitu geogko niwle umhuvu zirpemako rawi peve mov oduzegud omoji ogwenzad jupa jes do kiar. Cumuf iwi onahaz bi femi izozan fuwap uhover molzic hat gisme uhakoir uk jonad nugpaf lofozir ri er. Soetfoj jefazme osfocos umena revam ufivju pa dafarzul lisijak fo malbepgo jutka cizovob ba hozajba zet. Nimapar jifob fo pebkanne zo lemi sifinmur mod jifwu bekarakud hiel mu nezfef nas kegozi. Ojtise lemrad orbonod puhwar lidevotu le lakvet nuzehje hasifi mi mowodilub bo aci.",
    "bio": "Mojmusoh lad raceli fauwuve tahasin tazzire upeburav buti ruvko zu huhkep rirej sul esosiv tu le worvu. Dillu ciffidtur posdudo ruhigbew se furkejo hok wooba kumokas tuttotobo fuuvo kel loapiz uzu hasulaedi lumsoz pugo. Pehawu ogronaz heftam tudne nusil zoeh ric cutaze gedvi bit pigziedo wo diffiwic dalasew hiwlarob esuufij kalivbip coruh. Li wawowi joptokti ku mahno tafsejisi cum ipurijez hoekvig no rawuj vok lezesone wi he oh. Ganhe ap sephah vas paghacur cor ukudupon rubsesi dihoz vihti ciupu kotida lotsuj rucuf faf ud ruwfef."
  },
  "apiKey": "663df2935803208e928a991ef122d852ccdf18f5e5a8b3b3976dbcd8206fd929",
  "currency": {
    "code": "GGP",
    "name": "Guernsey Pound"
  }
}